[
    {
        "date": "2023-12-17",
        "id": 1,
        "customer": "John Doe",
        "email": "John.Doe@example.com",
        "phone": "1234567890",
        "comment": "Lorem ipsum dolor sit amet, consectetur adipiscing elit.",
        "archived": false
    },
    {
        "date": "2023-12-18",
        "id": 2,
        "customer": "Jane Smith",
        "email": "Jane.Smith@example.com",
        "phone": "0987654321",
        "comment": "Sed do eiusmod tempor incididunt ut labore et dolore magna aliqua.",
        "archived": false
    },
    {
        "date": "2023-12-19",
        "id": 3,
        "customer": "Josep Bonilla",
        "email": "Josep.Bonilla32@yahoo.com",
        "phone": "8848763694",
        "comment": "Est ea velit ut dolore cillum qui eu mollit velit exercitation esse deserunt ex amet ipsum ullamco velit reprehenderit consectetur magna aute do qui in voluptate cillum ex sunt enim eiusmod nulla.",
        "archived": false
    },
    {
        "date": "2023-12-20",
        "id": 4,
        "customer": "Michael Johnson",
        "email": "Michael.Johnson@example.com",
        "phone": "8765432109",
        "comment": "Ut enim ad minim veniam, quis nostrud exercitation ullamco laboris nisi ut aliquip ex ea commodo consequat.",
        "archived": false
    },
    {
        "date": "2023-12-21",
        "id": 5,
        "customer": "Emily Davis",
        "email": "Emily.Davis@example.com",
        "phone": "7654321098",
        "comment": "Duis aute irure dolor in reprehenderit in voluptate velit esse cillum dolore eu fugiat nulla pariatur.",
        "archived": false
    },
    {
        "date": "2023-12-22",
        "id": 6,
        "customer": "Christopher Martinez",
        "email": "Christopher.Martinez@example.com",
        "phone": "6543210987",
        "comment": "Excepteur sint occaecat cupidatat non proident, sunt in culpa qui officia deserunt mollit anim id est laborum.",
        "archived": false
    },
    {
        "date": "2023-12-23",
        "id": 7,
        "customer": "Sophia Rodriguez",
        "email": "Sophia.Rodriguez@example.com",
        "phone": "5432109876",
        "comment": "Consectetur adipisicing elit, sed do eiusmod tempor incididunt ut labore et dolore magna aliqua.",
        "archived": false
    },
    {
        "date": "2023-12-24",
        "id": 8,
        "customer": "William Brown",
        "email": "William.Brown@example.com",
        "phone": "4321098765",
        "comment": "Ut enim ad minim veniam, quis nostrud exercitation ullamco laboris nisi ut aliquip ex ea commodo consequat.",
        "archived": false
    },
    {
        "date": "2023-12-25",
        "id": 9,
        "customer": "Isabella Wilson",
        "email": "Isabella.Wilson@example.com",
        "phone": "3210987654",
        "comment": "Duis aute irure dolor in reprehenderit in voluptate velit esse cillum dolore eu fugiat nulla pariatur.",
        "archived": false
    },
    {
        "date": "2023-12-26",
        "id": 10,
        "customer": "James Anderson",
        "email": "James.Anderson@example.com",
        "phone": "2109876543",
        "comment": "Excepteur sint occaecat cupidatat non proident, sunt in culpa qui officia deserunt mollit anim id est laborum.",
        "archived": false
    },
    {
        "date": "2023-12-27",
        "id": 11,
        "customer": "Ava Thomas",
        "email": "Ava.Thomas@example.com",
        "phone": "1098765432",
        "comment": "Sed ut perspiciatis unde omnis iste natus error sit voluptatem accusantium doloremque laudantium.",
        "archived": false
    },
    {
        "date": "2023-12-28",
        "id": 12,
        "customer": "Oliver Taylor",
        "email": "Oliver.Taylor@example.com",
        "phone": "0987654321",
        "comment": "Nemo enim ipsam voluptatem quia voluptas sit aspernatur aut odit aut fugit.",
        "archived": false
    },
    {
        "date": "2023-12-29",
        "id": 13,
        "customer": "Mia Moore",
        "email": "Mia.Moore@example.com",
        "phone": "9876543210",
        "comment": "Neque porro quisquam est, qui dolorem ipsum quia dolor sit amet, consectetur, adipisci velit.",
        "archived": false
    },
    {
        "date": "2023-12-30",
        "id": 14,
        "customer": "Ethan Jackson",
        "email": "Ethan.Jackson@example.com",
        "phone": "8765432109",
        "comment": "Sed quia non numquam eius modi tempora incidunt ut labore et dolore magnam aliquam quaerat voluptatem.",
        "archived": false
    },
    {
        "date": "2023-12-31",
        "id": 15,
        "customer": "Charlotte White",
        "email": "Charlotte.White@example.com",
        "phone": "7654321098",
        "comment": "Ut enim ad minima veniam, quis nostrum exercitationem ullam corporis suscipit laboriosam, nisi ut aliquid ex ea commodi consequatur.",
        "archived": false
    },
    {
        "date": "2024-01-01",
        "id": 16,
        "customer": "Alexander Harris",
        "email": "Alexander.Harris@example.com",
        "phone": "6543210987",
        "comment": "Quis autem vel eum iure reprehenderit qui in ea voluptate velit esse quam nihil molestiae consequatur.",
        "archived": false
    },
    {
        "date": "2024-01-02",
        "id": 17,
        "customer": "Amelia Clark",
        "email": "Amelia.Clark@example.com",
        "phone": "5432109876",
        "comment": "Vel illum qui dolorem eum fugiat quo voluptas nulla pariatur.",
        "archived": false
    },
    {
        "date": "2024-01-03",
        "id": 18,
        "customer": "Henry Lewis",
        "email": "Henry.Lewis@example.com",
        "phone": "4321098765",
        "comment": "At vero eos et accusamus et iusto odio dignissimos ducimus qui blanditiis praesentium voluptatum deleniti atque corrupti quos dolores et quas molestias excepturi sint occaecati cupiditate non provident.",
        "archived": false
    },
    {
        "date": "2024-01-04",
        "id": 19,
        "customer": "Evelyn Walker",
        "email": "Evelyn.Walker@example.com",
        "phone": "3210987654",
        "comment": "Similique sunt in culpa qui officia deserunt mollitia animi, id est laborum et dolorum fuga.",
        "archived": false
    },
    {
        "date": "2024-01-05",
        "id": 20,
        "customer": "Daniel Hall",
        "email": "Daniel.Hall@example.com",
        "phone": "2109876543",
        "comment": "Et harum quidem rerum facilis est et expedita distinctio.",
        "archived": false
    }
]
